{
  "display": {
    "icon": {
      "item": "thebetweenlands:mud_brick_alcove"
    },
    "title": {
      "translate": "advancements.thebetweenlands.adventurer.i_think_you_urned_this.title"
    },
    "description": {
      "translate": "advancements.thebetweenlands.adventurer.i_think_you_urned_this.description"
    }
  },
  "parent": "thebetweenlands:adventurer/pothead",
  "criteria": {
     "urn1": {
          "trigger": "thebetweenlands:break_alcove_urn"
    },
    "urn2": {
            "trigger": "thebetweenlands:break_alcove_urn"
    },
    "urn3": {
           "trigger": "thebetweenlands:break_alcove_urn"
    },
    "urn4": {
           "trigger": "thebetweenlands:break_alcove_urn"
    },
    "urn5": {
           "trigger": "thebetweenlands:break_alcove_urn"
    },
    "urn6": {
           "trigger": "thebetweenlands:break_alcove_urn"
    },
    "urn7": {
           "trigger": "thebetweenlands:break_alcove_urn"
    },
    "urn8": {
          "trigger": "thebetweenlands:break_alcove_urn"
    },
    "urn9": {
           "trigger": "thebetweenlands:break_alcove_urn"
    },
    "urn10": {
          "trigger": "thebetweenlands:break_alcove_urn"
    },
    "urn11": {
           "trigger": "thebetweenlands:break_alcove_urn"
    },
    "urn12": {
          "trigger": "thebetweenlands:break_alcove_urn"
    },
    "urn13": {
           "trigger": "thebetweenlands:break_alcove_urn"
    },
    "urn14": {
         "trigger": "thebetweenlands:break_alcove_urn"
    },
    "urn15": {
          "trigger": "thebetweenlands:break_alcove_urn"
    },
    "urn16": {
          "trigger": "thebetweenlands:break_alcove_urn"
    },
    "urn17": {
          "trigger": "thebetweenlands:break_alcove_urn"
    },
    "urn18": {
          "trigger": "thebetweenlands:break_alcove_urn"
    },
    "urn19": {
         "trigger": "thebetweenlands:break_alcove_urn"
    },
    "urn20": {
           "trigger": "thebetweenlands:break_alcove_urn"
    }
  }
}